m8_core/__init__.py
m8_core/cli-simple.py
m8_core/cli-stable.py
m8_core/cli.py
m8_core/client.py
m8_core-0.1.2.dist-info/licenses/LICENSE
m8_core-0.1.2.dist-info/METADATA
m8_core-0.1.2.dist-info/WHEEL
m8_core-0.1.2.dist-info/entry_points.txt
m8_core-0.1.2.dist-info/top_level.txt
m8_core-0.1.2.dist-info/RECORD
