Metadata-Version: 2.4
Name: m8-core
Version: 0.1.2
Summary: High-performance Python client for the M8P Hypervisor and Agent Runtime.
Author-email: M8P Systems <info@enterstarts.com>
License: MIT License
Project-URL: Homepage, https://m8-site.desktop.farm
Project-URL: Bug Tracker, https://github.com/m8p-ai/m8-core-project/issues
Keywords: m8,llm,vector-db,agent,hypervisor
Classifier: Programming Language :: Python :: 3
Classifier: License :: OSI Approved :: MIT License
Classifier: Operating System :: OS Independent
Classifier: Intended Audience :: Developers
Classifier: Topic :: Scientific/Engineering :: Artificial Intelligence
Requires-Python: >=3.8
License-File: LICENSE
Requires-Dist: requests>=2.31.0
Dynamic: license-file
